geoambiental/Field.py
geoambiental/GeoCircle.py
geoambiental/Grid.py
geoambiental/Kernel.py
geoambiental/Line.py
geoambiental/Map.py
geoambiental/Point.py
geoambiental/PointArray.py
geoambiental/Polygon.py
geoambiental/PolygonArray.py
geoambiental/Trajectory.py
geoambiental/__init__.py
geoambiental/interfaces/IGeoRaster.py
geoambiental/interfaces/IGeoReference.py
geoambiental/interfaces/IGeoReferenceBounded.py
geoambiental/interfaces/IGeoReferenceFinite.py
geoambiental/interfaces/ITimeReference.py
geoambiental/interfaces/__init__.py
geoambiental/io/__init__.py
geoambiental/io/gpx.py
geoambiental/io/shp.py
geoambiental/operations/__init__.py
geoambiental/operations/distance.py
geoambiental/operations/in_polygon.py
geoambiental-0.1.0.dist-info/licenses/LICENSE
geoambiental-0.1.0.dist-info/WHEEL
geoambiental-0.1.0.dist-info/METADATA
geoambiental-0.1.0.dist-info/RECORD
