Metadata-Version: 2.4
Name: geoambiental
Version: 0.1.0
Summary: Geoambiental package
Home-page: https://github.com/IslasGECI/geoambiental
Author: Ciencia de Datos • GECI
Author-email: ciencia.datos@islas.org.mx
Requires-Python: >=3.8
Classifier: License :: OSI Approved :: GNU General Public License v3 or later (GPLv3+)
License-File: LICENSE
Requires-Dist: geoarea
Requires-Dist: geopandas
Requires-Dist: geopy
Requires-Dist: gpxpy
Requires-Dist: matplotlib
Requires-Dist: numpy
Requires-Dist: scipy
Requires-Dist: scikit-learn
Requires-Dist: utm
